Workbook

Sheet SETUP_RATES
A1: Truck Type | B1: Min Charge | C1: Rate/KM | D1: Included Hours | E1: OT Rate/Hr | F1: Helper Rate | G1: Fuel Surcharge % | H1: Maintenance/Trip | J1: GLOBAL SETTINGS
A2: 20 ftr - 6 wheels | B2: 6000 | C2: 136.5 | E2: 350 | H2: 0.15 | J2: Free Waiting Hours | K2: 1
A3: 16 ftr - 6 wheels | B3: 6000 | C3: 110 | E3: 250 | H3: 0.15 | J3: Waiting Rate/Hr | K3: 500
A4: 14 ftr - 6 wheels | B4: 5500 | C4: 105 | E4: 250 | H4: 0.15 | J4: Default VAT % | K4: 0.12
A5: 12 ftr - 6 wheels | B5: 5000 | C5: 105 | E5: 250 | H5: 0.15 | J5: Target Margin % | K5: 0.2
A6: 10 ftr - 4 wheels | B6: 4500 | C6: 100 | E6: 250 | H6: 0.15 | J6: Fuel Alert % vs Standard | K6: 0.15

Sheet SETUP_TRUCKS
A1: Truck ID | B1: Plate No | C1: Truck Type | D1: Capacity | E1: Fuel km/L | F1: Status | G1: Condition (1-5) | H1: Monthly Fixed Cost | I1: Notes
A2: V5 | B2: XHR 788 | C2: 10 ftr - 4 wheels | F2: Active | I2: SVC
A3: V6 | B3: REP 141 | C3: 14 ftr - 6 wheels | D3: 3 tons | E3: 8 | F3: Active
A4: V7 | B4: RFZ 534 | C4: 16 ftr - 6 wheels | D4: 3.5 tons | E4: 8 | F4: Active
A5: V9 | B5: XKD 180 | C5: 12 ftr - 6 wheels | D5: 2 tons | E5: 8 | F5: Active
A6: V10 | B6: RJB 646 | C6: 20 ftr - 6 wheels | D6: 6 tons | F6: Active
A7: V12 | B7: TQO 775 | C7: 14 ftr - 6 wheels | D7: 3 tons | E7: 8 | F7: Under Repair
A8: V13 | B8: UWI 887 | C8: 14 ftr - 6 wheels | D8: 3.5 tons | E8: 8 | F8: Active
A9: V15 | B9: RBH 578 | C9: 10 ftr - 6 wheels | F9: Active
A10: V16 | B10: UCC 523 | C10: 10 ftr - 4 wheels | F10: Active
A11: V17 | B11: WLL 732 | C11: 10 ftr - 4 wheels | F11: Active
A12: V18 | B12: RJE 141 | C12: 10 ftr - 4 wheels | F12: Active
A13: V20 | B13: URR 575 | C13: 10 ftr - 4 wheels | F13: Active
A14: V21 | B14: RHY 366 | C14: 10 ftr - 6 wheels | F14: Active
A15: V22 | B15: RHV 542 | C15: 14 ftr - 6 wheels | D15: 3 tons | E15: 8 | F15: Active
A16: V23 | B16: RJP 723 | C16: 10 ftr - 4 wheels | F16: Active
A17: ELF1 | B17: XAM 959 | C17: 14 ftr - 6 wheels | D17: 3 tons | E17: 8 | F17: Under Repair
A18: ELF2 | B18: XSH 957 | C18: 16 ftr - 6 wheels drop side | D18: 4 tons | F18: Active

Sheet SETUP_DRIVERS
A1: Driver ID | B1: Name | C1: Assigned Truck | D1: Rate Type (Daily/Trip) | E1: Rate | F1: Status | G1: Experience | H1: Notes
A2: 2013030 | B2: CARAGAY, ROGELIO JR. | C2: WLL 732 | D2: 600 | F2: Active
A3: 2026031 | B3: CAPALARAN , RONEL | C3: RJP 723 | D3: 600 | F3: Active
A4: 2016034 | B4: CORAÑES, RODNEY | C4: RJE 141 | D4: 600 | F4: Active
A5: 2010012 | B5: IGNACIO, PHILIP | C5: URR 575 | D5: 630 | F5: Active
A6: 2016032 | B6: LORETO, ANTONIO | C6: RBH 578 | D6: 675 | F6: Active
A7: 2025103 | B7: CASINOVA, ARMANDO | C7: XKD 180 | D7: 625 | F7: Active
A8: 2025025 | B8: LIBONGCOGON, RONALD | C8: NO PERMANENT TRUCK | D8: 0.15 | F8: Active
A9: 2013001 | B9: PREDILLA, NILO | C9: NO PERMANENT TRUCK | D9: 0.15 | F9: Active
A10: 2018007 | B10: PREDILLA , ALLAN JAY | C10: RHY 366 | D10: 600 | F10: Active

Sheet SETUP_HELPERS
A1: Helper ID | B1: Name | C1: Rate/Day | D1: Status | E1: Notes
A2: 2014035 | B2: BONTIGAO, FRANCIS | C2: 550 | D2: Active
A3: 2013001 | B3: CABANIGAN, JOEL | C3: 500 | D3: Active
A4: 2017007 | B4: CULA, JORDAN | C4: 500 | D4: Active
A5: 2026031 | B5: LANUZA, JC | C5: 525 | D5: Active
A6: 2017003 | B6: LIBONGCOGON, RENIL | C6: 500 | D6: Active
A7: 2023007 | B7: ONDOC, JUNNIFER | C7: 500 | D7: Active
A8: 2025110 | B8: ROQUE, JOHN | C8: 500 | D8: Active

Sheet CLIENTS
A1: Client ID | B1: Company Name | C1: Contact Person | D1: Mobile | E1: Email | F1: Payment Terms | G1: Avg Booking/Month | H1: Notes
B2: ROBINSONS APPLIANCES CORP | C2: MS. LINDSEY USQUISA | D2: 0998-841-4637 | E2: lindsey.usquisa@robinsonsretail.com.ph | F2: 30 DAYS | G2: 26 per cluster / 5 cluster
B3: ROBINSONS HANDYMAN INC | C3: MS. LINDSEY USQUISA | D3: 0998-841-4637 | E3: lindsey.usquisa@robinsonsretail.com.ph | F3: 30 DAYS | G3: 23 per cluster / 2 cluster
B4: UNITED RENRYSON MANUFACTURING OPC | C4: MS. JENNY ANCERO | D4: 0917-3159710 | E4: urmc.plant@gmail.com | F4: 1 WEEK
B5: BLOOMING VENTURES INC | C5: MS. KRIS DELOS SANTOS | D5: 0917-5555933 | E5: blooming.kris4@gmail.com | F5: 1 WEEK
B6: L & T DESIGN POWERHAUS | C6: MS. JOVY GOLLOSO | D6: 0917-9766744 | E6: jovy_golloso@yahoo.com | F6: 1 WEEK

Sheet BOOKINGS
A1: Booking ID | B1: Date | C1: Client ID | D1: Pickup | E1: Drop-off | F1: Distance (km) | G1: Truck Type | H1: Requested Date | I1: Requested Time | J1: Helpers Needed | K1: Cargo Type | L1: Status | M1: Quoted Amount | N1: Est. Base Charge | O1: Est. Helper Cost | P1: Est. Total Quote | Q1: Booking Month
N2: =IF(OR(F2="",G2=""),"",MAX(F2*VLOOKUP(G2,SETUP_RATES!$A:$H,3,FALSE),VLOOKUP(G2,SETUP_RATES!$A:$H,2,FALSE))) | O2: =IF(OR(J2="",G2=""),"",J2*VLOOKUP(G2,SETUP_RATES!$A:$H,6,FALSE)) | P2: =IF(N2="","",N2+IFERROR(O2,0)) | Q2: =IF(B2="","",TEXT(B2,"yyyy-mm"))
N3: =IF(OR(F3="",G3=""),"",MAX(F3*VLOOKUP(G3,SETUP_RATES!$A:$H,3,FALSE),VLOOKUP(G3,SETUP_RATES!$A:$H,2,FALSE))) | O3: =IF(OR(J3="",G3=""),"",J3*VLOOKUP(G3,SETUP_RATES!$A:$H,6,FALSE)) | P3: =IF(N3="","",N3+IFERROR(O3,0)) | Q3: =IF(B3="","",TEXT(B3,"yyyy-mm"))
N4: =IF(OR(F4="",G4=""),"",MAX(F4*VLOOKUP(G4,SETUP_RATES!$A:$H,3,FALSE),VLOOKUP(G4,SETUP_RATES!$A:$H,2,FALSE))) | O4: =IF(OR(J4="",G4=""),"",J4*VLOOKUP(G4,SETUP_RATES!$A:$H,6,FALSE)) | P4: =IF(N4="","",N4+IFERROR(O4,0)) | Q4: =IF(B4="","",TEXT(B4,"yyyy-mm"))
N5: =IF(OR(F5="",G5=""),"",MAX(F5*VLOOKUP(G5,SETUP_RATES!$A:$H,3,FALSE),VLOOKUP(G5,SETUP_RATES!$A:$H,2,FALSE))) | O5: =IF(OR(J5="",G5=""),"",J5*VLOOKUP(G5,SETUP_RATES!$A:$H,6,FALSE)) | P5: =IF(N5="","",N5+IFERROR(O5,0)) | Q5: =IF(B5="","",TEXT(B5,"yyyy-mm"))
N6: =IF(OR(F6="",G6=""),"",MAX(F6*VLOOKUP(G6,SETUP_RATES!$A:$H,3,FALSE),VLOOKUP(G6,SETUP_RATES!$A:$H,2,FALSE))) | O6: =IF(OR(J6="",G6=""),"",J6*VLOOKUP(G6,SETUP_RATES!$A:$H,6,FALSE)) | P6: =IF(N6="","",N6+IFERROR(O6,0)) | Q6: =IF(B6="","",TEXT(B6,"yyyy-mm"))
N7: =IF(OR(F7="",G7=""),"",MAX(F7*VLOOKUP(G7,SETUP_RATES!$A:$H,3,FALSE),VLOOKUP(G7,SETUP_RATES!$A:$H,2,FALSE))) | O7: =IF(OR(J7="",G7=""),"",J7*VLOOKUP(G7,SETUP_RATES!$A:$H,6,FALSE)) | P7: =IF(N7="","",N7+IFERROR(O7,0)) | Q7: =IF(B7="","",TEXT(B7,"yyyy-mm"))
N8: =IF(OR(F8="",G8=""),"",MAX(F8*VLOOKUP(G8,SETUP_RATES!$A:$H,3,FALSE),VLOOKUP(G8,SETUP_RATES!$A:$H,2,FALSE))) | O8: =IF(OR(J8="",G8=""),"",J8*VLOOKUP(G8,SETUP_RATES!$A:$H,6,FALSE)) | P8: =IF(N8="","",N8+IFERROR(O8,0)) | Q8: =IF(B8="","",TEXT(B8,"yyyy-mm"))
N9: =IF(OR(F9="",G9=""),"",MAX(F9*VLOOKUP(G9,SETUP_RATES!$A:$H,3,FALSE),VLOOKUP(G9,SETUP_RATES!$A:$H,2,FALSE))) | O9: =IF(OR(J9="",G9=""),"",J9*VLOOKUP(G9,SETUP_RATES!$A:$H,6,FALSE)) | P9: =IF(N9="","",N9+IFERROR(O9,0)) | Q9: =IF(B9="","",TEXT(B9,"yyyy-mm"))
N10: =IF(OR(F10="",G10=""),"",MAX(F10*VLOOKUP(G10,SETUP_RATES!$A:$H,3,FALSE),VLOOKUP(G10,SETUP_RATES!$A:$H,2,FALSE))) | O10: =IF(OR(J10="",G10=""),"",J10*VLOOKUP(G10,SETUP_RATES!$A:$H,6,FALSE)) | P10: =IF(N10="","",N10+IFERROR(O10,0)) | Q10: =IF(B10="","",TEXT(B10,"yyyy-mm"))
N11: =IF(OR(F11="",G11=""),"",MAX(F11*VLOOKUP(G11,SETUP_RATES!$A:$H,3,FALSE),VLOOKUP(G11,SETUP_RATES!$A:$H,2,FALSE))) | O11: =IF(OR(J11="",G11=""),"",J11*VLOOKUP(G11,SETUP_RATES!$A:$H,6,FALSE)) | P11: =IF(N11="","",N11+IFERROR(O11,0)) | Q11: =IF(B11="","",TEXT(B11,"yyyy-mm"))
N12: =IF(OR(F12="",G12=""),"",MAX(F12*VLOOKUP(G12,SETUP_RATES!$A:$H,3,FALSE),VLOOKUP(G12,SETUP_RATES!$A:$H,2,FALSE))) | O12: =IF(OR(J12="",G12=""),"",J12*VLOOKUP(G12,SETUP_RATES!$A:$H,6,FALSE)) | P12: =IF(N12="","",N12+IFERROR(O12,0)) | Q12: =IF(B12="","",TEXT(B12,"yyyy-mm"))
N13: =IF(OR(F13="",G13=""),"",MAX(F13*VLOOKUP(G13,SETUP_RATES!$A:$H,3,FALSE),VLOOKUP(G13,SETUP_RATES!$A:$H,2,FALSE))) | O13: =IF(OR(J13="",G13=""),"",J13*VLOOKUP(G13,SETUP_RATES!$A:$H,6,FALSE)) | P13: =IF(N13="","",N13+IFERROR(O13,0)) | Q13: =IF(B13="","",TEXT(B13,"yyyy-mm"))
... N500: =IF(OR(F500="",G500=""),"",MAX(F500*VLOOKUP(G500,SETUP_RATES!$A:$H,3,FALSE),VLOOKUP(G500,SETUP_RATES!$A:$H,2,FALSE))) | O500: =IF(OR(J500="",G500=""),"",J500*VLOOKUP(G500,SETUP_RATES!$A:$H,6,FALSE)) | P500: =IF(N500="","",N500+IFERROR(O500,0)) | Q500: =IF(B500="","",TEXT(B500,"yyyy-mm"))

Sheet DISPATCH
A1: Booking ID | B1: Truck ID | C1: Driver ID | D1: Helper ID(s) | E1: Dispatch Time | F1: Estimated End Time | G1: Status | H1: Trip Duration (Hrs) | I1: Dispatch Notes
H2: =IF(OR(E2="",F2=""),"",24*(F2-E2))
H3: =IF(OR(E3="",F3=""),"",24*(F3-E3))
H4: =IF(OR(E4="",F4=""),"",24*(F4-E4))
H5: =IF(OR(E5="",F5=""),"",24*(F5-E5))
H6: =IF(OR(E6="",F6=""),"",24*(F6-E6))
H7: =IF(OR(E7="",F7=""),"",24*(F7-E7))
H8: =IF(OR(E8="",F8=""),"",24*(F8-E8))
H9: =IF(OR(E9="",F9=""),"",24*(F9-E9))
H10: =IF(OR(E10="",F10=""),"",24*(F10-E10))
H11: =IF(OR(E11="",F11=""),"",24*(F11-E11))
H12: =IF(OR(E12="",F12=""),"",24*(F12-E12))
H13: =IF(OR(E13="",F13=""),"",24*(F13-E13))
... H500: =IF(OR(E500="",F500=""),"",24*(F500-E500))

Sheet TRIP_ACTUALS
A1: Booking ID | B1: Actual Start | C1: Actual End | D1: Fuel Used (L) | E1: Fuel Cost | F1: Toll | G1: Parking | H1: Waiting Hours | I1: OT Hours | J1: Issues | K1: Actual Duration (Hrs) | L1: Expected Fuel Cost | M1: Fuel Variance | N1: Completion Status | O1: Cost Notes
K2: =IF(OR(B2="",C2=""),"",24*(C2-B2)) | L2: =IF(A2="","",IFERROR(VLOOKUP(VLOOKUP(A2,BOOKINGS!$A:$Q,7,FALSE),SETUP_RATES!$A:$H,8,FALSE),0)) | M2: =IF(OR(E2="",L2=""),"",E2-L2) | N2: =IF(A2="","",IF(C2<>"","Completed","Open"))
K3: =IF(OR(B3="",C3=""),"",24*(C3-B3)) | L3: =IF(A3="","",IFERROR(VLOOKUP(VLOOKUP(A3,BOOKINGS!$A:$Q,7,FALSE),SETUP_RATES!$A:$H,8,FALSE),0)) | M3: =IF(OR(E3="",L3=""),"",E3-L3) | N3: =IF(A3="","",IF(C3<>"","Completed","Open"))
K4: =IF(OR(B4="",C4=""),"",24*(C4-B4)) | L4: =IF(A4="","",IFERROR(VLOOKUP(VLOOKUP(A4,BOOKINGS!$A:$Q,7,FALSE),SETUP_RATES!$A:$H,8,FALSE),0)) | M4: =IF(OR(E4="",L4=""),"",E4-L4) | N4: =IF(A4="","",IF(C4<>"","Completed","Open"))
K5: =IF(OR(B5="",C5=""),"",24*(C5-B5)) | L5: =IF(A5="","",IFERROR(VLOOKUP(VLOOKUP(A5,BOOKINGS!$A:$Q,7,FALSE),SETUP_RATES!$A:$H,8,FALSE),0)) | M5: =IF(OR(E5="",L5=""),"",E5-L5) | N5: =IF(A5="","",IF(C5<>"","Completed","Open"))
K6: =IF(OR(B6="",C6=""),"",24*(C6-B6)) | L6: =IF(A6="","",IFERROR(VLOOKUP(VLOOKUP(A6,BOOKINGS!$A:$Q,7,FALSE),SETUP_RATES!$A:$H,8,FALSE),0)) | M6: =IF(OR(E6="",L6=""),"",E6-L6) | N6: =IF(A6="","",IF(C6<>"","Completed","Open"))
K7: =IF(OR(B7="",C7=""),"",24*(C7-B7)) | L7: =IF(A7="","",IFERROR(VLOOKUP(VLOOKUP(A7,BOOKINGS!$A:$Q,7,FALSE),SETUP_RATES!$A:$H,8,FALSE),0)) | M7: =IF(OR(E7="",L7=""),"",E7-L7) | N7: =IF(A7="","",IF(C7<>"","Completed","Open"))
K8: =IF(OR(B8="",C8=""),"",24*(C8-B8)) | L8: =IF(A8="","",IFERROR(VLOOKUP(VLOOKUP(A8,BOOKINGS!$A:$Q,7,FALSE),SETUP_RATES!$A:$H,8,FALSE),0)) | M8: =IF(OR(E8="",L8=""),"",E8-L8) | N8: =IF(A8="","",IF(C8<>"","Completed","Open"))
K9: =IF(OR(B9="",C9=""),"",24*(C9-B9)) | L9: =IF(A9="","",IFERROR(VLOOKUP(VLOOKUP(A9,BOOKINGS!$A:$Q,7,FALSE),SETUP_RATES!$A:$H,8,FALSE),0)) | M9: =IF(OR(E9="",L9=""),"",E9-L9) | N9: =IF(A9="","",IF(C9<>"","Completed","Open"))
K10: =IF(OR(B10="",C10=""),"",24*(C10-B10)) | L10: =IF(A10="","",IFERROR(VLOOKUP(VLOOKUP(A10,BOOKINGS!$A:$Q,7,FALSE),SETUP_RATES!$A:$H,8,FALSE),0)) | M10: =IF(OR(E10="",L10=""),"",E10-L10) | N10: =IF(A10="","",IF(C10<>"","Completed","Open"))
K11: =IF(OR(B11="",C11=""),"",24*(C11-B11)) | L11: =IF(A11="","",IFERROR(VLOOKUP(VLOOKUP(A11,BOOKINGS!$A:$Q,7,FALSE),SETUP_RATES!$A:$H,8,FALSE),0)) | M11: =IF(OR(E11="",L11=""),"",E11-L11) | N11: =IF(A11="","",IF(C11<>"","Completed","Open"))
K12: =IF(OR(B12="",C12=""),"",24*(C12-B12)) | L12: =IF(A12="","",IFERROR(VLOOKUP(VLOOKUP(A12,BOOKINGS!$A:$Q,7,FALSE),SETUP_RATES!$A:$H,8,FALSE),0)) | M12: =IF(OR(E12="",L12=""),"",E12-L12) | N12: =IF(A12="","",IF(C12<>"","Completed","Open"))
K13: =IF(OR(B13="",C13=""),"",24*(C13-B13)) | L13: =IF(A13="","",IFERROR(VLOOKUP(VLOOKUP(A13,BOOKINGS!$A:$Q,7,FALSE),SETUP_RATES!$A:$H,8,FALSE),0)) | M13: =IF(OR(E13="",L13=""),"",E13-L13) | N13: =IF(A13="","",IF(C13<>"","Completed","Open"))
... K500: =IF(OR(B500="",C500=""),"",24*(C500-B500)) | L500: =IF(A500="","",IFERROR(VLOOKUP(VLOOKUP(A500,BOOKINGS!$A:$Q,7,FALSE),SETUP_RATES!$A:$H,8,FALSE),0)) | M500: =IF(OR(E500="",L500=""),"",E500-L500) | N500: =IF(A500="","",IF(C500<>"","Completed","Open"))

Sheet COSTING
A1: Booking ID | B1: Base Charge | C1: Helper Cost | D1: Waiting Cost | E1: OT Cost | F1: Fuel Cost | G1: Toll | H1: Maintenance Cost | I1: Total Cost | J1: Revenue | K1: Variance vs Quote | L1: Cost % of Revenue
A2: =IF(BOOKINGS!A2="","",BOOKINGS!A2) | B2: =IF(A2="","",MAX(VLOOKUP(A2,BOOKINGS!$A:$Q,6,FALSE)*VLOOKUP(VLOOKUP(A2,BOOKINGS!$A:$Q,7,FALSE),SETUP_RATES!$A:$H,3,FALSE),VLOOKUP(VLOOKUP(A2,BOOKINGS!$A:$Q,7,FALSE),SETUP_RATES!$A:$H,2,FALSE))) | C2: =IF(A2="","",VLOOKUP(A2,BOOKINGS!$A:$Q,10,FALSE)*VLOOKUP(VLOOKUP(A2,BOOKINGS!$A:$Q,7,FALSE),SETUP_RATES!$A:$H,6,FALSE)) | D2: =IF(A2="","",MAX(0,VLOOKUP(A2,TRIP_ACTUALS!$A:$O,8,FALSE)-SETUP_RATES!$K$2)*SETUP_RATES!$K$3) | E2: =IF(A2="","",VLOOKUP(A2,TRIP_ACTUALS!$A:$O,9,FALSE)*VLOOKUP(VLOOKUP(A2,BOOKINGS!$A:$Q,7,FALSE),SETUP_RATES!$A:$H,5,FALSE)) | F2: =IF(A2="","",IFERROR(VLOOKUP(A2,TRIP_ACTUALS!$A:$O,5,FALSE),0)) | G2: =IF(A2="","",IFERROR(VLOOKUP(A2,TRIP_ACTUALS!$A:$O,6,FALSE),0)+IFERROR(VLOOKUP(A2,TRIP_ACTUALS!$A:$O,7,FALSE),0)) | H2: =IF(A2="","",IFERROR(VLOOKUP(VLOOKUP(A2,BOOKINGS!$A:$Q,7,FALSE),SETUP_RATES!$A:$H,8,FALSE),0)) | I2: =IF(A2="","",SUM(B2:H2)) | J2: =IF(A2="","",IFERROR(VLOOKUP(A2,BOOKINGS!$A:$Q,13,FALSE),0)) | K2: =IF(A2="","",J2-I2) | L2: =IFERROR(I2/J2,"")
A3: =IF(BOOKINGS!A3="","",BOOKINGS!A3) | B3: =IF(A3="","",MAX(VLOOKUP(A3,BOOKINGS!$A:$Q,6,FALSE)*VLOOKUP(VLOOKUP(A3,BOOKINGS!$A:$Q,7,FALSE),SETUP_RATES!$A:$H,3,FALSE),VLOOKUP(VLOOKUP(A3,BOOKINGS!$A:$Q,7,FALSE),SETUP_RATES!$A:$H,2,FALSE))) | C3: =IF(A3="","",VLOOKUP(A3,BOOKINGS!$A:$Q,10,FALSE)*VLOOKUP(VLOOKUP(A3,BOOKINGS!$A:$Q,7,FALSE),SETUP_RATES!$A:$H,6,FALSE)) | D3: =IF(A3="","",MAX(0,VLOOKUP(A3,TRIP_ACTUALS!$A:$O,8,FALSE)-SETUP_RATES!$K$2)*SETUP_RATES!$K$3) | E3: =IF(A3="","",VLOOKUP(A3,TRIP_ACTUALS!$A:$O,9,FALSE)*VLOOKUP(VLOOKUP(A3,BOOKINGS!$A:$Q,7,FALSE),SETUP_RATES!$A:$H,5,FALSE)) | F3: =IF(A3="","",IFERROR(VLOOKUP(A3,TRIP_ACTUALS!$A:$O,5,FALSE),0)) | G3: =IF(A3="","",IFERROR(VLOOKUP(A3,TRIP_ACTUALS!$A:$O,6,FALSE),0)+IFERROR(VLOOKUP(A3,TRIP_ACTUALS!$A:$O,7,FALSE),0)) | H3: =IF(A3="","",IFERROR(VLOOKUP(VLOOKUP(A3,BOOKINGS!$A:$Q,7,FALSE),SETUP_RATES!$A:$H,8,FALSE),0)) | I3: =IF(A3="","",SUM(B3:H3)) | J3: =IF(A3="","",IFERROR(VLOOKUP(A3,BOOKINGS!$A:$Q,13,FALSE),0)) | K3: =IF(A3="","",J3-I3) | L3: =IFERROR(I3/J3,"")
A4: =IF(BOOKINGS!A4="","",BOOKINGS!A4) | B4: =IF(A4="","",MAX(VLOOKUP(A4,BOOKINGS!$A:$Q,6,FALSE)*VLOOKUP(VLOOKUP(A4,BOOKINGS!$A:$Q,7,FALSE),SETUP_RATES!$A:$H,3,FALSE),VLOOKUP(VLOOKUP(A4,BOOKINGS!$A:$Q,7,FALSE),SETUP_RATES!$A:$H,2,FALSE))) | C4: =IF(A4="","",VLOOKUP(A4,BOOKINGS!$A:$Q,10,FALSE)*VLOOKUP(VLOOKUP(A4,BOOKINGS!$A:$Q,7,FALSE),SETUP_RATES!$A:$H,6,FALSE)) | D4: =IF(A4="","",MAX(0,VLOOKUP(A4,TRIP_ACTUALS!$A:$O,8,FALSE)-SETUP_RATES!$K$2)*SETUP_RATES!$K$3) | E4: =IF(A4="","",VLOOKUP(A4,TRIP_ACTUALS!$A:$O,9,FALSE)*VLOOKUP(VLOOKUP(A4,BOOKINGS!$A:$Q,7,FALSE),SETUP_RATES!$A:$H,5,FALSE)) | F4: =IF(A4="","",IFERROR(VLOOKUP(A4,TRIP_ACTUALS!$A:$O,5,FALSE),0)) | G4: =IF(A4="","",IFERROR(VLOOKUP(A4,TRIP_ACTUALS!$A:$O,6,FALSE),0)+IFERROR(VLOOKUP(A4,TRIP_ACTUALS!$A:$O,7,FALSE),0)) | H4: =IF(A4="","",IFERROR(VLOOKUP(VLOOKUP(A4,BOOKINGS!$A:$Q,7,FALSE),SETUP_RATES!$A:$H,8,FALSE),0)) | I4: =IF(A4="","",SUM(B4:H4)) | J4: =IF(A4="","",IFERROR(VLOOKUP(A4,BOOKINGS!$A:$Q,13,FALSE),0)) | K4: =IF(A4="","",J4-I4) | L4: =IFERROR(I4/J4,"")
A5: =IF(BOOKINGS!A5="","",BOOKINGS!A5) | B5: =IF(A5="","",MAX(VLOOKUP(A5,BOOKINGS!$A:$Q,6,FALSE)*VLOOKUP(VLOOKUP(A5,BOOKINGS!$A:$Q,7,FALSE),SETUP_RATES!$A:$H,3,FALSE),VLOOKUP(VLOOKUP(A5,BOOKINGS!$A:$Q,7,FALSE),SETUP_RATES!$A:$H,2,FALSE))) | C5: =IF(A5="","",VLOOKUP(A5,BOOKINGS!$A:$Q,10,FALSE)*VLOOKUP(VLOOKUP(A5,BOOKINGS!$A:$Q,7,FALSE),SETUP_RATES!$A:$H,6,FALSE)) | D5: =IF(A5="","",MAX(0,VLOOKUP(A5,TRIP_ACTUALS!$A:$O,8,FALSE)-SETUP_RATES!$K$2)*SETUP_RATES!$K$3) | E5: =IF(A5="","",VLOOKUP(A5,TRIP_ACTUALS!$A:$O,9,FALSE)*VLOOKUP(VLOOKUP(A5,BOOKINGS!$A:$Q,7,FALSE),SETUP_RATES!$A:$H,5,FALSE)) | F5: =IF(A5="","",IFERROR(VLOOKUP(A5,TRIP_ACTUALS!$A:$O,5,FALSE),0)) | G5: =IF(A5="","",IFERROR(VLOOKUP(A5,TRIP_ACTUALS!$A:$O,6,FALSE),0)+IFERROR(VLOOKUP(A5,TRIP_ACTUALS!$A:$O,7,FALSE),0)) | H5: =IF(A5="","",IFERROR(VLOOKUP(VLOOKUP(A5,BOOKINGS!$A:$Q,7,FALSE),SETUP_RATES!$A:$H,8,FALSE),0)) | I5: =IF(A5="","",SUM(B5:H5)) | J5: =IF(A5="","",IFERROR(VLOOKUP(A5,BOOKINGS!$A:$Q,13,FALSE),0)) | K5: =IF(A5="","",J5-I5) | L5: =IFERROR(I5/J5,"")
A6: =IF(BOOKINGS!A6="","",BOOKINGS!A6) | B6: =IF(A6="","",MAX(VLOOKUP(A6,BOOKINGS!$A:$Q,6,FALSE)*VLOOKUP(VLOOKUP(A6,BOOKINGS!$A:$Q,7,FALSE),SETUP_RATES!$A:$H,3,FALSE),VLOOKUP(VLOOKUP(A6,BOOKINGS!$A:$Q,7,FALSE),SETUP_RATES!$A:$H,2,FALSE))) | C6: =IF(A6="","",VLOOKUP(A6,BOOKINGS!$A:$Q,10,FALSE)*VLOOKUP(VLOOKUP(A6,BOOKINGS!$A:$Q,7,FALSE),SETUP_RATES!$A:$H,6,FALSE)) | D6: =IF(A6="","",MAX(0,VLOOKUP(A6,TRIP_ACTUALS!$A:$O,8,FALSE)-SETUP_RATES!$K$2)*SETUP_RATES!$K$3) | E6: =IF(A6="","",VLOOKUP(A6,TRIP_ACTUALS!$A:$O,9,FALSE)*VLOOKUP(VLOOKUP(A6,BOOKINGS!$A:$Q,7,FALSE),SETUP_RATES!$A:$H,5,FALSE)) | F6: =IF(A6="","",IFERROR(VLOOKUP(A6,TRIP_ACTUALS!$A:$O,5,FALSE),0)) | G6: =IF(A6="","",IFERROR(VLOOKUP(A6,TRIP_ACTUALS!$A:$O,6,FALSE),0)+IFERROR(VLOOKUP(A6,TRIP_ACTUALS!$A:$O,7,FALSE),0)) | H6: =IF(A6="","",IFERROR(VLOOKUP(VLOOKUP(A6,BOOKINGS!$A:$Q,7,FALSE),SETUP_RATES!$A:$H,8,FALSE),0)) | I6: =IF(A6="","",SUM(B6:H6)) | J6: =IF(A6="","",IFERROR(VLOOKUP(A6,BOOKINGS!$A:$Q,13,FALSE),0)) | K6: =IF(A6="","",J6-I6) | L6: =IFERROR(I6/J6,"")
A7: =IF(BOOKINGS!A7="","",BOOKINGS!A7) | B7: =IF(A7="","",MAX(VLOOKUP(A7,BOOKINGS!$A:$Q,6,FALSE)*VLOOKUP(VLOOKUP(A7,BOOKINGS!$A:$Q,7,FALSE),SETUP_RATES!$A:$H,3,FALSE),VLOOKUP(VLOOKUP(A7,BOOKINGS!$A:$Q,7,FALSE),SETUP_RATES!$A:$H,2,FALSE))) | C7: =IF(A7="","",VLOOKUP(A7,BOOKINGS!$A:$Q,10,FALSE)*VLOOKUP(VLOOKUP(A7,BOOKINGS!$A:$Q,7,FALSE),SETUP_RATES!$A:$H,6,FALSE)) | D7: =IF(A7="","",MAX(0,VLOOKUP(A7,TRIP_ACTUALS!$A:$O,8,FALSE)-SETUP_RATES!$K$2)*SETUP_RATES!$K$3) | E7: =IF(A7="","",VLOOKUP(A7,TRIP_ACTUALS!$A:$O,9,FALSE)*VLOOKUP(VLOOKUP(A7,BOOKINGS!$A:$Q,7,FALSE),SETUP_RATES!$A:$H,5,FALSE)) | F7: =IF(A7="","",IFERROR(VLOOKUP(A7,TRIP_ACTUALS!$A:$O,5,FALSE),0)) | G7: =IF(A7="","",IFERROR(VLOOKUP(A7,TRIP_ACTUALS!$A:$O,6,FALSE),0)+IFERROR(VLOOKUP(A7,TRIP_ACTUALS!$A:$O,7,FALSE),0)) | H7: =IF(A7="","",IFERROR(VLOOKUP(VLOOKUP(A7,BOOKINGS!$A:$Q,7,FALSE),SETUP_RATES!$A:$H,8,FALSE),0)) | I7: =IF(A7="","",SUM(B7:H7)) | J7: =IF(A7="","",IFERROR(VLOOKUP(A7,BOOKINGS!$A:$Q,13,FALSE),0)) | K7: =IF(A7="","",J7-I7) | L7: =IFERROR(I7/J7,"")
A8: =IF(BOOKINGS!A8="","",BOOKINGS!A8) | B8: =IF(A8="","",MAX(VLOOKUP(A8,BOOKINGS!$A:$Q,6,FALSE)*VLOOKUP(VLOOKUP(A8,BOOKINGS!$A:$Q,7,FALSE),SETUP_RATES!$A:$H,3,FALSE),VLOOKUP(VLOOKUP(A8,BOOKINGS!$A:$Q,7,FALSE),SETUP_RATES!$A:$H,2,FALSE))) | C8: =IF(A8="","",VLOOKUP(A8,BOOKINGS!$A:$Q,10,FALSE)*VLOOKUP(VLOOKUP(A8,BOOKINGS!$A:$Q,7,FALSE),SETUP_RATES!$A:$H,6,FALSE)) | D8: =IF(A8="","",MAX(0,VLOOKUP(A8,TRIP_ACTUALS!$A:$O,8,FALSE)-SETUP_RATES!$K$2)*SETUP_RATES!$K$3) | E8: =IF(A8="","",VLOOKUP(A8,TRIP_ACTUALS!$A:$O,9,FALSE)*VLOOKUP(VLOOKUP(A8,BOOKINGS!$A:$Q,7,FALSE),SETUP_RATES!$A:$H,5,FALSE)) | F8: =IF(A8="","",IFERROR(VLOOKUP(A8,TRIP_ACTUALS!$A:$O,5,FALSE),0)) | G8: =IF(A8="","",IFERROR(VLOOKUP(A8,TRIP_ACTUALS!$A:$O,6,FALSE),0)+IFERROR(VLOOKUP(A8,TRIP_ACTUALS!$A:$O,7,FALSE),0)) | H8: =IF(A8="","",IFERROR(VLOOKUP(VLOOKUP(A8,BOOKINGS!$A:$Q,7,FALSE),SETUP_RATES!$A:$H,8,FALSE),0)) | I8: =IF(A8="","",SUM(B8:H8)) | J8: =IF(A8="","",IFERROR(VLOOKUP(A8,BOOKINGS!$A:$Q,13,FALSE),0)) | K8: =IF(A8="","",J8-I8) | L8: =IFERROR(I8/J8,"")
A9: =IF(BOOKINGS!A9="","",BOOKINGS!A9) | B9: =IF(A9="","",MAX(VLOOKUP(A9,BOOKINGS!$A:$Q,6,FALSE)*VLOOKUP(VLOOKUP(A9,BOOKINGS!$A:$Q,7,FALSE),SETUP_RATES!$A:$H,3,FALSE),VLOOKUP(VLOOKUP(A9,BOOKINGS!$A:$Q,7,FALSE),SETUP_RATES!$A:$H,2,FALSE))) | C9: =IF(A9="","",VLOOKUP(A9,BOOKINGS!$A:$Q,10,FALSE)*VLOOKUP(VLOOKUP(A9,BOOKINGS!$A:$Q,7,FALSE),SETUP_RATES!$A:$H,6,FALSE)) | D9: =IF(A9="","",MAX(0,VLOOKUP(A9,TRIP_ACTUALS!$A:$O,8,FALSE)-SETUP_RATES!$K$2)*SETUP_RATES!$K$3) | E9: =IF(A9="","",VLOOKUP(A9,TRIP_ACTUALS!$A:$O,9,FALSE)*VLOOKUP(VLOOKUP(A9,BOOKINGS!$A:$Q,7,FALSE),SETUP_RATES!$A:$H,5,FALSE)) | F9: =IF(A9="","",IFERROR(VLOOKUP(A9,TRIP_ACTUALS!$A:$O,5,FALSE),0)) | G9: =IF(A9="","",IFERROR(VLOOKUP(A9,TRIP_ACTUALS!$A:$O,6,FALSE),0)+IFERROR(VLOOKUP(A9,TRIP_ACTUALS!$A:$O,7,FALSE),0)) | H9: =IF(A9="","",IFERROR(VLOOKUP(VLOOKUP(A9,BOOKINGS!$A:$Q,7,FALSE),SETUP_RATES!$A:$H,8,FALSE),0)) | I9: =IF(A9="","",SUM(B9:H9)) | J9: =IF(A9="","",IFERROR(VLOOKUP(A9,BOOKINGS!$A:$Q,13,FALSE),0)) | K9: =IF(A9="","",J9-I9) | L9: =IFERROR(I9/J9,"")
A10: =IF(BOOKINGS!A10="","",BOOKINGS!A10) | B10: =IF(A10="","",MAX(VLOOKUP(A10,BOOKINGS!$A:$Q,6,FALSE)*VLOOKUP(VLOOKUP(A10,BOOKINGS!$A:$Q,7,FALSE),SETUP_RATES!$A:$H,3,FALSE),VLOOKUP(VLOOKUP(A10,BOOKINGS!$A:$Q,7,FALSE),SETUP_RATES!$A:$H,2,FALSE))) | C10: =IF(A10="","",VLOOKUP(A10,BOOKINGS!$A:$Q,10,FALSE)*VLOOKUP(VLOOKUP(A10,BOOKINGS!$A:$Q,7,FALSE),SETUP_RATES!$A:$H,6,FALSE)) | D10: =IF(A10="","",MAX(0,VLOOKUP(A10,TRIP_ACTUALS!$A:$O,8,FALSE)-SETUP_RATES!$K$2)*SETUP_RATES!$K$3) | E10: =IF(A10="","",VLOOKUP(A10,TRIP_ACTUALS!$A:$O,9,FALSE)*VLOOKUP(VLOOKUP(A10,BOOKINGS!$A:$Q,7,FALSE),SETUP_RATES!$A:$H,5,FALSE)) | F10: =IF(A10="","",IFERROR(VLOOKUP(A10,TRIP_ACTUALS!$A:$O,5,FALSE),0)) | G10: =IF(A10="","",IFERROR(VLOOKUP(A10,TRIP_ACTUALS!$A:$O,6,FALSE),0)+IFERROR(VLOOKUP(A10,TRIP_ACTUALS!$A:$O,7,FALSE),0)) | H10: =IF(A10="","",IFERROR(VLOOKUP(VLOOKUP(A10,BOOKINGS!$A:$Q,7,FALSE),SETUP_RATES!$A:$H,8,FALSE),0)) | I10: =IF(A10="","",SUM(B10:H10)) | J10: =IF(A10="","",IFERROR(VLOOKUP(A10,BOOKINGS!$A:$Q,13,FALSE),0)) | K10: =IF(A10="","",J10-I10) | L10: =IFERROR(I10/J10,"")
A11: =IF(BOOKINGS!A11="","",BOOKINGS!A11) | B11: =IF(A11="","",MAX(VLOOKUP(A11,BOOKINGS!$A:$Q,6,FALSE)*VLOOKUP(VLOOKUP(A11,BOOKINGS!$A:$Q,7,FALSE),SETUP_RATES!$A:$H,3,FALSE),VLOOKUP(VLOOKUP(A11,BOOKINGS!$A:$Q,7,FALSE),SETUP_RATES!$A:$H,2,FALSE))) | C11: =IF(A11="","",VLOOKUP(A11,BOOKINGS!$A:$Q,10,FALSE)*VLOOKUP(VLOOKUP(A11,BOOKINGS!$A:$Q,7,FALSE),SETUP_RATES!$A:$H,6,FALSE)) | D11: =IF(A11="","",MAX(0,VLOOKUP(A11,TRIP_ACTUALS!$A:$O,8,FALSE)-SETUP_RATES!$K$2)*SETUP_RATES!$K$3) | E11: =IF(A11="","",VLOOKUP(A11,TRIP_ACTUALS!$A:$O,9,FALSE)*VLOOKUP(VLOOKUP(A11,BOOKINGS!$A:$Q,7,FALSE),SETUP_RATES!$A:$H,5,FALSE)) | F11: =IF(A11="","",IFERROR(VLOOKUP(A11,TRIP_ACTUALS!$A:$O,5,FALSE),0)) | G11: =IF(A11="","",IFERROR(VLOOKUP(A11,TRIP_ACTUALS!$A:$O,6,FALSE),0)+IFERROR(VLOOKUP(A11,TRIP_ACTUALS!$A:$O,7,FALSE),0)) | H11: =IF(A11="","",IFERROR(VLOOKUP(VLOOKUP(A11,BOOKINGS!$A:$Q,7,FALSE),SETUP_RATES!$A:$H,8,FALSE),0)) | I11: =IF(A11="","",SUM(B11:H11)) | J11: =IF(A11="","",IFERROR(VLOOKUP(A11,BOOKINGS!$A:$Q,13,FALSE),0)) | K11: =IF(A11="","",J11-I11) | L11: =IFERROR(I11/J11,"")
A12: =IF(BOOKINGS!A12="","",BOOKINGS!A12) | B12: =IF(A12="","",MAX(VLOOKUP(A12,BOOKINGS!$A:$Q,6,FALSE)*VLOOKUP(VLOOKUP(A12,BOOKINGS!$A:$Q,7,FALSE),SETUP_RATES!$A:$H,3,FALSE),VLOOKUP(VLOOKUP(A12,BOOKINGS!$A:$Q,7,FALSE),SETUP_RATES!$A:$H,2,FALSE))) | C12: =IF(A12="","",VLOOKUP(A12,BOOKINGS!$A:$Q,10,FALSE)*VLOOKUP(VLOOKUP(A12,BOOKINGS!$A:$Q,7,FALSE),SETUP_RATES!$A:$H,6,FALSE)) | D12: =IF(A12="","",MAX(0,VLOOKUP(A12,TRIP_ACTUALS!$A:$O,8,FALSE)-SETUP_RATES!$K$2)*SETUP_RATES!$K$3) | E12: =IF(A12="","",VLOOKUP(A12,TRIP_ACTUALS!$A:$O,9,FALSE)*VLOOKUP(VLOOKUP(A12,BOOKINGS!$A:$Q,7,FALSE),SETUP_RATES!$A:$H,5,FALSE)) | F12: =IF(A12="","",IFERROR(VLOOKUP(A12,TRIP_ACTUALS!$A:$O,5,FALSE),0)) | G12: =IF(A12="","",IFERROR(VLOOKUP(A12,TRIP_ACTUALS!$A:$O,6,FALSE),0)+IFERROR(VLOOKUP(A12,TRIP_ACTUALS!$A:$O,7,FALSE),0)) | H12: =IF(A12="","",IFERROR(VLOOKUP(VLOOKUP(A12,BOOKINGS!$A:$Q,7,FALSE),SETUP_RATES!$A:$H,8,FALSE),0)) | I12: =IF(A12="","",SUM(B12:H12)) | J12: =IF(A12="","",IFERROR(VLOOKUP(A12,BOOKINGS!$A:$Q,13,FALSE),0)) | K12: =IF(A12="","",J12-I12) | L12: =IFERROR(I12/J12,"")
A13: =IF(BOOKINGS!A13="","",BOOKINGS!A13) | B13: =IF(A13="","",MAX(VLOOKUP(A13,BOOKINGS!$A:$Q,6,FALSE)*VLOOKUP(VLOOKUP(A13,BOOKINGS!$A:$Q,7,FALSE),SETUP_RATES!$A:$H,3,FALSE),VLOOKUP(VLOOKUP(A13,BOOKINGS!$A:$Q,7,FALSE),SETUP_RATES!$A:$H,2,FALSE))) | C13: =IF(A13="","",VLOOKUP(A13,BOOKINGS!$A:$Q,10,FALSE)*VLOOKUP(VLOOKUP(A13,BOOKINGS!$A:$Q,7,FALSE),SETUP_RATES!$A:$H,6,FALSE)) | D13: =IF(A13="","",MAX(0,VLOOKUP(A13,TRIP_ACTUALS!$A:$O,8,FALSE)-SETUP_RATES!$K$2)*SETUP_RATES!$K$3) | E13: =IF(A13="","",VLOOKUP(A13,TRIP_ACTUALS!$A:$O,9,FALSE)*VLOOKUP(VLOOKUP(A13,BOOKINGS!$A:$Q,7,FALSE),SETUP_RATES!$A:$H,5,FALSE)) | F13: =IF(A13="","",IFERROR(VLOOKUP(A13,TRIP_ACTUALS!$A:$O,5,FALSE),0)) | G13: =IF(A13="","",IFERROR(VLOOKUP(A13,TRIP_ACTUALS!$A:$O,6,FALSE),0)+IFERROR(VLOOKUP(A13,TRIP_ACTUALS!$A:$O,7,FALSE),0)) | H13: =IF(A13="","",IFERROR(VLOOKUP(VLOOKUP(A13,BOOKINGS!$A:$Q,7,FALSE),SETUP_RATES!$A:$H,8,FALSE),0)) | I13: =IF(A13="","",SUM(B13:H13)) | J13: =IF(A13="","",IFERROR(VLOOKUP(A13,BOOKINGS!$A:$Q,13,FALSE),0)) | K13: =IF(A13="","",J13-I13) | L13: =IFERROR(I13/J13,"")
... A500: =IF(BOOKINGS!A500="","",BOOKINGS!A500) | B500: =IF(A500="","",MAX(VLOOKUP(A500,BOOKINGS!$A:$Q,6,FALSE)*VLOOKUP(VLOOKUP(A500,BOOKINGS!$A:$Q,7,FALSE),SETUP_RATES!$A:$H,3,FALSE),VLOOKUP(VLOOKUP(A500,BOOKINGS!$A:$Q,7,FALSE),SETUP_RATES!$A:$H,2,FALSE))) | C500: =IF(A500="","",VLOOKUP(A500,BOOKINGS!$A:$Q,10,FALSE)*VLOOKUP(VLOOKUP(A500,BOOKINGS!$A:$Q,7,FALSE),SETUP_RATES!$A:$H,6,FALSE)) | D500: =IF(A500="","",MAX(0,VLOOKUP(A500,TRIP_ACTUALS!$A:$O,8,FALSE)-SETUP_RATES!$K$2)*SETUP_RATES!$K$3) | E500: =IF(A500="","",VLOOKUP(A500,TRIP_ACTUALS!$A:$O,9,FALSE)*VLOOKUP(VLOOKUP(A500,BOOKINGS!$A:$Q,7,FALSE),SETUP_RATES!$A:$H,5,FALSE)) | F500: =IF(A500="","",IFERROR(VLOOKUP(A500,TRIP_ACTUALS!$A:$O,5,FALSE),0)) | G500: =IF(A500="","",IFERROR(VLOOKUP(A500,TRIP_ACTUALS!$A:$O,6,FALSE),0)+IFERROR(VLOOKUP(A500,TRIP_ACTUALS!$A:$O,7,FALSE),0)) | H500: =IF(A500="","",IFERROR(VLOOKUP(VLOOKUP(A500,BOOKINGS!$A:$Q,7,FALSE),SETUP_RATES!$A:$H,8,FALSE),0)) | I500: =IF(A500="","",SUM(B500:H500)) | J500: =IF(A500="","",IFERROR(VLOOKUP(A500,BOOKINGS!$A:$Q,13,FALSE),0)) | K500: =IF(A500="","",J500-I500) | L500: =IFERROR(I500/J500,"")

Sheet PROFITABILITY
A1: Booking ID | B1: Revenue | C1: Total Cost | D1: Profit | E1: Margin % | F1: Target Margin % | G1: Above Target? | H1: Profit Status
A2: =IF(COSTING!A2="","",COSTING!A2) | B2: =IF(A2="","",COSTING!J2) | C2: =IF(A2="","",COSTING!I2) | D2: =IF(A2="","",B2-C2) | E2: =IFERROR(D2/B2,"") | F2: =IF(A2="","",SETUP_RATES!$K$5) | G2: =IF(A2="","",IF(E2>=F2,"YES","NO")) | H2: =IF(A2="","",IF(D2<0,"LOSS",IF(E2<F2,"LOW MARGIN","HEALTHY")))
A3: =IF(COSTING!A3="","",COSTING!A3) | B3: =IF(A3="","",COSTING!J3) | C3: =IF(A3="","",COSTING!I3) | D3: =IF(A3="","",B3-C3) | E3: =IFERROR(D3/B3,"") | F3: =IF(A3="","",SETUP_RATES!$K$5) | G3: =IF(A3="","",IF(E3>=F3,"YES","NO")) | H3: =IF(A3="","",IF(D3<0,"LOSS",IF(E3<F3,"LOW MARGIN","HEALTHY")))
A4: =IF(COSTING!A4="","",COSTING!A4) | B4: =IF(A4="","",COSTING!J4) | C4: =IF(A4="","",COSTING!I4) | D4: =IF(A4="","",B4-C4) | E4: =IFERROR(D4/B4,"") | F4: =IF(A4="","",SETUP_RATES!$K$5) | G4: =IF(A4="","",IF(E4>=F4,"YES","NO")) | H4: =IF(A4="","",IF(D4<0,"LOSS",IF(E4<F4,"LOW MARGIN","HEALTHY")))
A5: =IF(COSTING!A5="","",COSTING!A5) | B5: =IF(A5="","",COSTING!J5) | C5: =IF(A5="","",COSTING!I5) | D5: =IF(A5="","",B5-C5) | E5: =IFERROR(D5/B5,"") | F5: =IF(A5="","",SETUP_RATES!$K$5) | G5: =IF(A5="","",IF(E5>=F5,"YES","NO")) | H5: =IF(A5="","",IF(D5<0,"LOSS",IF(E5<F5,"LOW MARGIN","HEALTHY")))
A6: =IF(COSTING!A6="","",COSTING!A6) | B6: =IF(A6="","",COSTING!J6) | C6: =IF(A6="","",COSTING!I6) | D6: =IF(A6="","",B6-C6) | E6: =IFERROR(D6/B6,"") | F6: =IF(A6="","",SETUP_RATES!$K$5) | G6: =IF(A6="","",IF(E6>=F6,"YES","NO")) | H6: =IF(A6="","",IF(D6<0,"LOSS",IF(E6<F6,"LOW MARGIN","HEALTHY")))
A7: =IF(COSTING!A7="","",COSTING!A7) | B7: =IF(A7="","",COSTING!J7) | C7: =IF(A7="","",COSTING!I7) | D7: =IF(A7="","",B7-C7) | E7: =IFERROR(D7/B7,"") | F7: =IF(A7="","",SETUP_RATES!$K$5) | G7: =IF(A7="","",IF(E7>=F7,"YES","NO")) | H7: =IF(A7="","",IF(D7<0,"LOSS",IF(E7<F7,"LOW MARGIN","HEALTHY")))
A8: =IF(COSTING!A8="","",COSTING!A8) | B8: =IF(A8="","",COSTING!J8) | C8: =IF(A8="","",COSTING!I8) | D8: =IF(A8="","",B8-C8) | E8: =IFERROR(D8/B8,"") | F8: =IF(A8="","",SETUP_RATES!$K$5) | G8: =IF(A8="","",IF(E8>=F8,"YES","NO")) | H8: =IF(A8="","",IF(D8<0,"LOSS",IF(E8<F8,"LOW MARGIN","HEALTHY")))
A9: =IF(COSTING!A9="","",COSTING!A9) | B9: =IF(A9="","",COSTING!J9) | C9: =IF(A9="","",COSTING!I9) | D9: =IF(A9="","",B9-C9) | E9: =IFERROR(D9/B9,"") | F9: =IF(A9="","",SETUP_RATES!$K$5) | G9: =IF(A9="","",IF(E9>=F9,"YES","NO")) | H9: =IF(A9="","",IF(D9<0,"LOSS",IF(E9<F9,"LOW MARGIN","HEALTHY")))
A10: =IF(COSTING!A10="","",COSTING!A10) | B10: =IF(A10="","",COSTING!J10) | C10: =IF(A10="","",COSTING!I10) | D10: =IF(A10="","",B10-C10) | E10: =IFERROR(D10/B10,"") | F10: =IF(A10="","",SETUP_RATES!$K$5) | G10: =IF(A10="","",IF(E10>=F10,"YES","NO")) | H10: =IF(A10="","",IF(D10<0,"LOSS",IF(E10<F10,"LOW MARGIN","HEALTHY")))
A11: =IF(COSTING!A11="","",COSTING!A11) | B11: =IF(A11="","",COSTING!J11) | C11: =IF(A11="","",COSTING!I11) | D11: =IF(A11="","",B11-C11) | E11: =IFERROR(D11/B11,"") | F11: =IF(A11="","",SETUP_RATES!$K$5) | G11: =IF(A11="","",IF(E11>=F11,"YES","NO")) | H11: =IF(A11="","",IF(D11<0,"LOSS",IF(E11<F11,"LOW MARGIN","HEALTHY")))
A12: =IF(COSTING!A12="","",COSTING!A12) | B12: =IF(A12="","",COSTING!J12) | C12: =IF(A12="","",COSTING!I12) | D12: =IF(A12="","",B12-C12) | E12: =IFERROR(D12/B12,"") | F12: =IF(A12="","",SETUP_RATES!$K$5) | G12: =IF(A12="","",IF(E12>=F12,"YES","NO")) | H12: =IF(A12="","",IF(D12<0,"LOSS",IF(E12<F12,"LOW MARGIN","HEALTHY")))
A13: =IF(COSTING!A13="","",COSTING!A13) | B13: =IF(A13="","",COSTING!J13) | C13: =IF(A13="","",COSTING!I13) | D13: =IF(A13="","",B13-C13) | E13: =IFERROR(D13/B13,"") | F13: =IF(A13="","",SETUP_RATES!$K$5) | G13: =IF(A13="","",IF(E13>=F13,"YES","NO")) | H13: =IF(A13="","",IF(D13<0,"LOSS",IF(E13<F13,"LOW MARGIN","HEALTHY")))
... A500: =IF(COSTING!A500="","",COSTING!A500) | B500: =IF(A500="","",COSTING!J500) | C500: =IF(A500="","",COSTING!I500) | D500: =IF(A500="","",B500-C500) | E500: =IFERROR(D500/B500,"") | F500: =IF(A500="","",SETUP_RATES!$K$5) | G500: =IF(A500="","",IF(E500>=F500,"YES","NO")) | H500: =IF(A500="","",IF(D500<0,"LOSS",IF(E500<F500,"LOW MARGIN","HEALTHY")))

Sheet BILLING
A1: Booking ID | B1: Invoice No | C1: Date Billed | D1: Amount Billed | E1: VAT | F1: Total Invoice | G1: Status | H1: Due Date | I1: Collection Status
A2: =IF(PROFITABILITY!A2="","",PROFITABILITY!A2) | B2: =IF(A2="","","INV-"&TEXT(ROW()-1,"0000")) | C2: =IF(A2="","",IFERROR(VLOOKUP(A2,BOOKINGS!$A:$Q,8,FALSE),BOOKINGS!B2)) | D2: =IF(A2="","",PROFITABILITY!B2) | E2: =IF(A2="","",SETUP_RATES!$K$4) | F2: =IF(A2="","",D2*(1+E2)) | G2: =IF(A2="","",IF(H2<TODAY(),IF(I2<>"Paid","Overdue","Billed"),"Billed")) | H2: =IF(C2="","",C2+IFERROR(VLOOKUP(VLOOKUP(A2,BOOKINGS!$A:$Q,3,FALSE),CLIENTS!$A:$H,6,FALSE),30)) | I2: =IF(A2="","",IFERROR(VLOOKUP(B2,COLLECTIONS!$A:$I,7,FALSE),"Unpaid"))
A3: =IF(PROFITABILITY!A3="","",PROFITABILITY!A3) | B3: =IF(A3="","","INV-"&TEXT(ROW()-1,"0000")) | C3: =IF(A3="","",IFERROR(VLOOKUP(A3,BOOKINGS!$A:$Q,8,FALSE),BOOKINGS!B3)) | D3: =IF(A3="","",PROFITABILITY!B3) | E3: =IF(A3="","",SETUP_RATES!$K$4) | F3: =IF(A3="","",D3*(1+E3)) | G3: =IF(A3="","",IF(H3<TODAY(),IF(I3<>"Paid","Overdue","Billed"),"Billed")) | H3: =IF(C3="","",C3+IFERROR(VLOOKUP(VLOOKUP(A3,BOOKINGS!$A:$Q,3,FALSE),CLIENTS!$A:$H,6,FALSE),30)) | I3: =IF(A3="","",IFERROR(VLOOKUP(B3,COLLECTIONS!$A:$I,7,FALSE),"Unpaid"))
A4: =IF(PROFITABILITY!A4="","",PROFITABILITY!A4) | B4: =IF(A4="","","INV-"&TEXT(ROW()-1,"0000")) | C4: =IF(A4="","",IFERROR(VLOOKUP(A4,BOOKINGS!$A:$Q,8,FALSE),BOOKINGS!B4)) | D4: =IF(A4="","",PROFITABILITY!B4) | E4: =IF(A4="","",SETUP_RATES!$K$4) | F4: =IF(A4="","",D4*(1+E4)) | G4: =IF(A4="","",IF(H4<TODAY(),IF(I4<>"Paid","Overdue","Billed"),"Billed")) | H4: =IF(C4="","",C4+IFERROR(VLOOKUP(VLOOKUP(A4,BOOKINGS!$A:$Q,3,FALSE),CLIENTS!$A:$H,6,FALSE),30)) | I4: =IF(A4="","",IFERROR(VLOOKUP(B4,COLLECTIONS!$A:$I,7,FALSE),"Unpaid"))
A5: =IF(PROFITABILITY!A5="","",PROFITABILITY!A5) | B5: =IF(A5="","","INV-"&TEXT(ROW()-1,"0000")) | C5: =IF(A5="","",IFERROR(VLOOKUP(A5,BOOKINGS!$A:$Q,8,FALSE),BOOKINGS!B5)) | D5: =IF(A5="","",PROFITABILITY!B5) | E5: =IF(A5="","",SETUP_RATES!$K$4) | F5: =IF(A5="","",D5*(1+E5)) | G5: =IF(A5="","",IF(H5<TODAY(),IF(I5<>"Paid","Overdue","Billed"),"Billed")) | H5: =IF(C5="","",C5+IFERROR(VLOOKUP(VLOOKUP(A5,BOOKINGS!$A:$Q,3,FALSE),CLIENTS!$A:$H,6,FALSE),30)) | I5: =IF(A5="","",IFERROR(VLOOKUP(B5,COLLECTIONS!$A:$I,7,FALSE),"Unpaid"))
A6: =IF(PROFITABILITY!A6="","",PROFITABILITY!A6) | B6: =IF(A6="","","INV-"&TEXT(ROW()-1,"0000")) | C6: =IF(A6="","",IFERROR(VLOOKUP(A6,BOOKINGS!$A:$Q,8,FALSE),BOOKINGS!B6)) | D6: =IF(A6="","",PROFITABILITY!B6) | E6: =IF(A6="","",SETUP_RATES!$K$4) | F6: =IF(A6="","",D6*(1+E6)) | G6: =IF(A6="","",IF(H6<TODAY(),IF(I6<>"Paid","Overdue","Billed"),"Billed")) | H6: =IF(C6="","",C6+IFERROR(VLOOKUP(VLOOKUP(A6,BOOKINGS!$A:$Q,3,FALSE),CLIENTS!$A:$H,6,FALSE),30)) | I6: =IF(A6="","",IFERROR(VLOOKUP(B6,COLLECTIONS!$A:$I,7,FALSE),"Unpaid"))
A7: =IF(PROFITABILITY!A7="","",PROFITABILITY!A7) | B7: =IF(A7="","","INV-"&TEXT(ROW()-1,"0000")) | C7: =IF(A7="","",IFERROR(VLOOKUP(A7,BOOKINGS!$A:$Q,8,FALSE),BOOKINGS!B7)) | D7: =IF(A7="","",PROFITABILITY!B7) | E7: =IF(A7="","",SETUP_RATES!$K$4) | F7: =IF(A7="","",D7*(1+E7)) | G7: =IF(A7="","",IF(H7<TODAY(),IF(I7<>"Paid","Overdue","Billed"),"Billed")) | H7: =IF(C7="","",C7+IFERROR(VLOOKUP(VLOOKUP(A7,BOOKINGS!$A:$Q,3,FALSE),CLIENTS!$A:$H,6,FALSE),30)) | I7: =IF(A7="","",IFERROR(VLOOKUP(B7,COLLECTIONS!$A:$I,7,FALSE),"Unpaid"))
A8: =IF(PROFITABILITY!A8="","",PROFITABILITY!A8) | B8: =IF(A8="","","INV-"&TEXT(ROW()-1,"0000")) | C8: =IF(A8="","",IFERROR(VLOOKUP(A8,BOOKINGS!$A:$Q,8,FALSE),BOOKINGS!B8)) | D8: =IF(A8="","",PROFITABILITY!B8) | E8: =IF(A8="","",SETUP_RATES!$K$4) | F8: =IF(A8="","",D8*(1+E8)) | G8: =IF(A8="","",IF(H8<TODAY(),IF(I8<>"Paid","Overdue","Billed"),"Billed")) | H8: =IF(C8="","",C8+IFERROR(VLOOKUP(VLOOKUP(A8,BOOKINGS!$A:$Q,3,FALSE),CLIENTS!$A:$H,6,FALSE),30)) | I8: =IF(A8="","",IFERROR(VLOOKUP(B8,COLLECTIONS!$A:$I,7,FALSE),"Unpaid"))
A9: =IF(PROFITABILITY!A9="","",PROFITABILITY!A9) | B9: =IF(A9="","","INV-"&TEXT(ROW()-1,"0000")) | C9: =IF(A9="","",IFERROR(VLOOKUP(A9,BOOKINGS!$A:$Q,8,FALSE),BOOKINGS!B9)) | D9: =IF(A9="","",PROFITABILITY!B9) | E9: =IF(A9="","",SETUP_RATES!$K$4) | F9: =IF(A9="","",D9*(1+E9)) | G9: =IF(A9="","",IF(H9<TODAY(),IF(I9<>"Paid","Overdue","Billed"),"Billed")) | H9: =IF(C9="","",C9+IFERROR(VLOOKUP(VLOOKUP(A9,BOOKINGS!$A:$Q,3,FALSE),CLIENTS!$A:$H,6,FALSE),30)) | I9: =IF(A9="","",IFERROR(VLOOKUP(B9,COLLECTIONS!$A:$I,7,FALSE),"Unpaid"))
A10: =IF(PROFITABILITY!A10="","",PROFITABILITY!A10) | B10: =IF(A10="","","INV-"&TEXT(ROW()-1,"0000")) | C10: =IF(A10="","",IFERROR(VLOOKUP(A10,BOOKINGS!$A:$Q,8,FALSE),BOOKINGS!B10)) | D10: =IF(A10="","",PROFITABILITY!B10) | E10: =IF(A10="","",SETUP_RATES!$K$4) | F10: =IF(A10="","",D10*(1+E10)) | G10: =IF(A10="","",IF(H10<TODAY(),IF(I10<>"Paid","Overdue","Billed"),"Billed")) | H10: =IF(C10="","",C10+IFERROR(VLOOKUP(VLOOKUP(A10,BOOKINGS!$A:$Q,3,FALSE),CLIENTS!$A:$H,6,FALSE),30)) | I10: =IF(A10="","",IFERROR(VLOOKUP(B10,COLLECTIONS!$A:$I,7,FALSE),"Unpaid"))
A11: =IF(PROFITABILITY!A11="","",PROFITABILITY!A11) | B11: =IF(A11="","","INV-"&TEXT(ROW()-1,"0000")) | C11: =IF(A11="","",IFERROR(VLOOKUP(A11,BOOKINGS!$A:$Q,8,FALSE),BOOKINGS!B11)) | D11: =IF(A11="","",PROFITABILITY!B11) | E11: =IF(A11="","",SETUP_RATES!$K$4) | F11: =IF(A11="","",D11*(1+E11)) | G11: =IF(A11="","",IF(H11<TODAY(),IF(I11<>"Paid","Overdue","Billed"),"Billed")) | H11: =IF(C11="","",C11+IFERROR(VLOOKUP(VLOOKUP(A11,BOOKINGS!$A:$Q,3,FALSE),CLIENTS!$A:$H,6,FALSE),30)) | I11: =IF(A11="","",IFERROR(VLOOKUP(B11,COLLECTIONS!$A:$I,7,FALSE),"Unpaid"))
A12: =IF(PROFITABILITY!A12="","",PROFITABILITY!A12) | B12: =IF(A12="","","INV-"&TEXT(ROW()-1,"0000")) | C12: =IF(A12="","",IFERROR(VLOOKUP(A12,BOOKINGS!$A:$Q,8,FALSE),BOOKINGS!B12)) | D12: =IF(A12="","",PROFITABILITY!B12) | E12: =IF(A12="","",SETUP_RATES!$K$4) | F12: =IF(A12="","",D12*(1+E12)) | G12: =IF(A12="","",IF(H12<TODAY(),IF(I12<>"Paid","Overdue","Billed"),"Billed")) | H12: =IF(C12="","",C12+IFERROR(VLOOKUP(VLOOKUP(A12,BOOKINGS!$A:$Q,3,FALSE),CLIENTS!$A:$H,6,FALSE),30)) | I12: =IF(A12="","",IFERROR(VLOOKUP(B12,COLLECTIONS!$A:$I,7,FALSE),"Unpaid"))
A13: =IF(PROFITABILITY!A13="","",PROFITABILITY!A13) | B13: =IF(A13="","","INV-"&TEXT(ROW()-1,"0000")) | C13: =IF(A13="","",IFERROR(VLOOKUP(A13,BOOKINGS!$A:$Q,8,FALSE),BOOKINGS!B13)) | D13: =IF(A13="","",PROFITABILITY!B13) | E13: =IF(A13="","",SETUP_RATES!$K$4) | F13: =IF(A13="","",D13*(1+E13)) | G13: =IF(A13="","",IF(H13<TODAY(),IF(I13<>"Paid","Overdue","Billed"),"Billed")) | H13: =IF(C13="","",C13+IFERROR(VLOOKUP(VLOOKUP(A13,BOOKINGS!$A:$Q,3,FALSE),CLIENTS!$A:$H,6,FALSE),30)) | I13: =IF(A13="","",IFERROR(VLOOKUP(B13,COLLECTIONS!$A:$I,7,FALSE),"Unpaid"))
... A500: =IF(PROFITABILITY!A500="","",PROFITABILITY!A500) | B500: =IF(A500="","","INV-"&TEXT(ROW()-1,"0000")) | C500: =IF(A500="","",IFERROR(VLOOKUP(A500,BOOKINGS!$A:$Q,8,FALSE),BOOKINGS!B500)) | D500: =IF(A500="","",PROFITABILITY!B500) | E500: =IF(A500="","",SETUP_RATES!$K$4) | F500: =IF(A500="","",D500*(1+E500)) | G500: =IF(A500="","",IF(H500<TODAY(),IF(I500<>"Paid","Overdue","Billed"),"Billed")) | H500: =IF(C500="","",C500+IFERROR(VLOOKUP(VLOOKUP(A500,BOOKINGS!$A:$Q,3,FALSE),CLIENTS!$A:$H,6,FALSE),30)) | I500: =IF(A500="","",IFERROR(VLOOKUP(B500,COLLECTIONS!$A:$I,7,FALSE),"Unpaid"))

Sheet COLLECTIONS
A1: Invoice No | B1: Client | C1: Amount Due | D1: Amount Paid | E1: Balance | F1: Date Paid | G1: Status | H1: Aging Days | I1: Aging Bucket
A2: =IF(BILLING!B2="","",BILLING!B2) | B2: =IF(A2="","",IFERROR(VLOOKUP(VLOOKUP(VLOOKUP(A2,BILLING!$B:$I,7,FALSE),BOOKINGS!$A:$Q,3,FALSE),CLIENTS!$A:$H,2,FALSE),"")) | C2: =IF(A2="","",IFERROR(VLOOKUP(A2,BILLING!$B:$I,5,FALSE),0)) | E2: =IF(A2="","",C2-IFERROR(D2,0)) | G2: =IF(A2="","",IF(E2<=0,"Paid",IF(D2>0,"Partial","Unpaid"))) | H2: =IF(OR(A2="",F2=""),"",F2-VLOOKUP(A2,BILLING!$B:$I,7,FALSE)) | I2: =IF(A2="","",IF(E2<=0,"Current",IF(TODAY()-VLOOKUP(A2,BILLING!$B:$I,7,FALSE)<=30,"0-30 Days",IF(TODAY()-VLOOKUP(A2,BILLING!$B:$I,7,FALSE)<=60,"31-60 Days","61+ Days"))))
A3: =IF(BILLING!B3="","",BILLING!B3) | B3: =IF(A3="","",IFERROR(VLOOKUP(VLOOKUP(VLOOKUP(A3,BILLING!$B:$I,7,FALSE),BOOKINGS!$A:$Q,3,FALSE),CLIENTS!$A:$H,2,FALSE),"")) | C3: =IF(A3="","",IFERROR(VLOOKUP(A3,BILLING!$B:$I,5,FALSE),0)) | E3: =IF(A3="","",C3-IFERROR(D3,0)) | G3: =IF(A3="","",IF(E3<=0,"Paid",IF(D3>0,"Partial","Unpaid"))) | H3: =IF(OR(A3="",F3=""),"",F3-VLOOKUP(A3,BILLING!$B:$I,7,FALSE)) | I3: =IF(A3="","",IF(E3<=0,"Current",IF(TODAY()-VLOOKUP(A3,BILLING!$B:$I,7,FALSE)<=30,"0-30 Days",IF(TODAY()-VLOOKUP(A3,BILLING!$B:$I,7,FALSE)<=60,"31-60 Days","61+ Days"))))
A4: =IF(BILLING!B4="","",BILLING!B4) | B4: =IF(A4="","",IFERROR(VLOOKUP(VLOOKUP(VLOOKUP(A4,BILLING!$B:$I,7,FALSE),BOOKINGS!$A:$Q,3,FALSE),CLIENTS!$A:$H,2,FALSE),"")) | C4: =IF(A4="","",IFERROR(VLOOKUP(A4,BILLING!$B:$I,5,FALSE),0)) | E4: =IF(A4="","",C4-IFERROR(D4,0)) | G4: =IF(A4="","",IF(E4<=0,"Paid",IF(D4>0,"Partial","Unpaid"))) | H4: =IF(OR(A4="",F4=""),"",F4-VLOOKUP(A4,BILLING!$B:$I,7,FALSE)) | I4: =IF(A4="","",IF(E4<=0,"Current",IF(TODAY()-VLOOKUP(A4,BILLING!$B:$I,7,FALSE)<=30,"0-30 Days",IF(TODAY()-VLOOKUP(A4,BILLING!$B:$I,7,FALSE)<=60,"31-60 Days","61+ Days"))))
A5: =IF(BILLING!B5="","",BILLING!B5) | B5: =IF(A5="","",IFERROR(VLOOKUP(VLOOKUP(VLOOKUP(A5,BILLING!$B:$I,7,FALSE),BOOKINGS!$A:$Q,3,FALSE),CLIENTS!$A:$H,2,FALSE),"")) | C5: =IF(A5="","",IFERROR(VLOOKUP(A5,BILLING!$B:$I,5,FALSE),0)) | E5: =IF(A5="","",C5-IFERROR(D5,0)) | G5: =IF(A5="","",IF(E5<=0,"Paid",IF(D5>0,"Partial","Unpaid"))) | H5: =IF(OR(A5="",F5=""),"",F5-VLOOKUP(A5,BILLING!$B:$I,7,FALSE)) | I5: =IF(A5="","",IF(E5<=0,"Current",IF(TODAY()-VLOOKUP(A5,BILLING!$B:$I,7,FALSE)<=30,"0-30 Days",IF(TODAY()-VLOOKUP(A5,BILLING!$B:$I,7,FALSE)<=60,"31-60 Days","61+ Days"))))
A6: =IF(BILLING!B6="","",BILLING!B6) | B6: =IF(A6="","",IFERROR(VLOOKUP(VLOOKUP(VLOOKUP(A6,BILLING!$B:$I,7,FALSE),BOOKINGS!$A:$Q,3,FALSE),CLIENTS!$A:$H,2,FALSE),"")) | C6: =IF(A6="","",IFERROR(VLOOKUP(A6,BILLING!$B:$I,5,FALSE),0)) | E6: =IF(A6="","",C6-IFERROR(D6,0)) | G6: =IF(A6="","",IF(E6<=0,"Paid",IF(D6>0,"Partial","Unpaid"))) | H6: =IF(OR(A6="",F6=""),"",F6-VLOOKUP(A6,BILLING!$B:$I,7,FALSE)) | I6: =IF(A6="","",IF(E6<=0,"Current",IF(TODAY()-VLOOKUP(A6,BILLING!$B:$I,7,FALSE)<=30,"0-30 Days",IF(TODAY()-VLOOKUP(A6,BILLING!$B:$I,7,FALSE)<=60,"31-60 Days","61+ Days"))))
A7: =IF(BILLING!B7="","",BILLING!B7) | B7: =IF(A7="","",IFERROR(VLOOKUP(VLOOKUP(VLOOKUP(A7,BILLING!$B:$I,7,FALSE),BOOKINGS!$A:$Q,3,FALSE),CLIENTS!$A:$H,2,FALSE),"")) | C7: =IF(A7="","",IFERROR(VLOOKUP(A7,BILLING!$B:$I,5,FALSE),0)) | E7: =IF(A7="","",C7-IFERROR(D7,0)) | G7: =IF(A7="","",IF(E7<=0,"Paid",IF(D7>0,"Partial","Unpaid"))) | H7: =IF(OR(A7="",F7=""),"",F7-VLOOKUP(A7,BILLING!$B:$I,7,FALSE)) | I7: =IF(A7="","",IF(E7<=0,"Current",IF(TODAY()-VLOOKUP(A7,BILLING!$B:$I,7,FALSE)<=30,"0-30 Days",IF(TODAY()-VLOOKUP(A7,BILLING!$B:$I,7,FALSE)<=60,"31-60 Days","61+ Days"))))
A8: =IF(BILLING!B8="","",BILLING!B8) | B8: =IF(A8="","",IFERROR(VLOOKUP(VLOOKUP(VLOOKUP(A8,BILLING!$B:$I,7,FALSE),BOOKINGS!$A:$Q,3,FALSE),CLIENTS!$A:$H,2,FALSE),"")) | C8: =IF(A8="","",IFERROR(VLOOKUP(A8,BILLING!$B:$I,5,FALSE),0)) | E8: =IF(A8="","",C8-IFERROR(D8,0)) | G8: =IF(A8="","",IF(E8<=0,"Paid",IF(D8>0,"Partial","Unpaid"))) | H8: =IF(OR(A8="",F8=""),"",F8-VLOOKUP(A8,BILLING!$B:$I,7,FALSE)) | I8: =IF(A8="","",IF(E8<=0,"Current",IF(TODAY()-VLOOKUP(A8,BILLING!$B:$I,7,FALSE)<=30,"0-30 Days",IF(TODAY()-VLOOKUP(A8,BILLING!$B:$I,7,FALSE)<=60,"31-60 Days","61+ Days"))))
A9: =IF(BILLING!B9="","",BILLING!B9) | B9: =IF(A9="","",IFERROR(VLOOKUP(VLOOKUP(VLOOKUP(A9,BILLING!$B:$I,7,FALSE),BOOKINGS!$A:$Q,3,FALSE),CLIENTS!$A:$H,2,FALSE),"")) | C9: =IF(A9="","",IFERROR(VLOOKUP(A9,BILLING!$B:$I,5,FALSE),0)) | E9: =IF(A9="","",C9-IFERROR(D9,0)) | G9: =IF(A9="","",IF(E9<=0,"Paid",IF(D9>0,"Partial","Unpaid"))) | H9: =IF(OR(A9="",F9=""),"",F9-VLOOKUP(A9,BILLING!$B:$I,7,FALSE)) | I9: =IF(A9="","",IF(E9<=0,"Current",IF(TODAY()-VLOOKUP(A9,BILLING!$B:$I,7,FALSE)<=30,"0-30 Days",IF(TODAY()-VLOOKUP(A9,BILLING!$B:$I,7,FALSE)<=60,"31-60 Days","61+ Days"))))
A10: =IF(BILLING!B10="","",BILLING!B10) | B10: =IF(A10="","",IFERROR(VLOOKUP(VLOOKUP(VLOOKUP(A10,BILLING!$B:$I,7,FALSE),BOOKINGS!$A:$Q,3,FALSE),CLIENTS!$A:$H,2,FALSE),"")) | C10: =IF(A10="","",IFERROR(VLOOKUP(A10,BILLING!$B:$I,5,FALSE),0)) | E10: =IF(A10="","",C10-IFERROR(D10,0)) | G10: =IF(A10="","",IF(E10<=0,"Paid",IF(D10>0,"Partial","Unpaid"))) | H10: =IF(OR(A10="",F10=""),"",F10-VLOOKUP(A10,BILLING!$B:$I,7,FALSE)) | I10: =IF(A10="","",IF(E10<=0,"Current",IF(TODAY()-VLOOKUP(A10,BILLING!$B:$I,7,FALSE)<=30,"0-30 Days",IF(TODAY()-VLOOKUP(A10,BILLING!$B:$I,7,FALSE)<=60,"31-60 Days","61+ Days"))))
A11: =IF(BILLING!B11="","",BILLING!B11) | B11: =IF(A11="","",IFERROR(VLOOKUP(VLOOKUP(VLOOKUP(A11,BILLING!$B:$I,7,FALSE),BOOKINGS!$A:$Q,3,FALSE),CLIENTS!$A:$H,2,FALSE),"")) | C11: =IF(A11="","",IFERROR(VLOOKUP(A11,BILLING!$B:$I,5,FALSE),0)) | E11: =IF(A11="","",C11-IFERROR(D11,0)) | G11: =IF(A11="","",IF(E11<=0,"Paid",IF(D11>0,"Partial","Unpaid"))) | H11: =IF(OR(A11="",F11=""),"",F11-VLOOKUP(A11,BILLING!$B:$I,7,FALSE)) | I11: =IF(A11="","",IF(E11<=0,"Current",IF(TODAY()-VLOOKUP(A11,BILLING!$B:$I,7,FALSE)<=30,"0-30 Days",IF(TODAY()-VLOOKUP(A11,BILLING!$B:$I,7,FALSE)<=60,"31-60 Days","61+ Days"))))
A12: =IF(BILLING!B12="","",BILLING!B12) | B12: =IF(A12="","",IFERROR(VLOOKUP(VLOOKUP(VLOOKUP(A12,BILLING!$B:$I,7,FALSE),BOOKINGS!$A:$Q,3,FALSE),CLIENTS!$A:$H,2,FALSE),"")) | C12: =IF(A12="","",IFERROR(VLOOKUP(A12,BILLING!$B:$I,5,FALSE),0)) | E12: =IF(A12="","",C12-IFERROR(D12,0)) | G12: =IF(A12="","",IF(E12<=0,"Paid",IF(D12>0,"Partial","Unpaid"))) | H12: =IF(OR(A12="",F12=""),"",F12-VLOOKUP(A12,BILLING!$B:$I,7,FALSE)) | I12: =IF(A12="","",IF(E12<=0,"Current",IF(TODAY()-VLOOKUP(A12,BILLING!$B:$I,7,FALSE)<=30,"0-30 Days",IF(TODAY()-VLOOKUP(A12,BILLING!$B:$I,7,FALSE)<=60,"31-60 Days","61+ Days"))))
A13: =IF(BILLING!B13="","",BILLING!B13) | B13: =IF(A13="","",IFERROR(VLOOKUP(VLOOKUP(VLOOKUP(A13,BILLING!$B:$I,7,FALSE),BOOKINGS!$A:$Q,3,FALSE),CLIENTS!$A:$H,2,FALSE),"")) | C13: =IF(A13="","",IFERROR(VLOOKUP(A13,BILLING!$B:$I,5,FALSE),0)) | E13: =IF(A13="","",C13-IFERROR(D13,0)) | G13: =IF(A13="","",IF(E13<=0,"Paid",IF(D13>0,"Partial","Unpaid"))) | H13: =IF(OR(A13="",F13=""),"",F13-VLOOKUP(A13,BILLING!$B:$I,7,FALSE)) | I13: =IF(A13="","",IF(E13<=0,"Current",IF(TODAY()-VLOOKUP(A13,BILLING!$B:$I,7,FALSE)<=30,"0-30 Days",IF(TODAY()-VLOOKUP(A13,BILLING!$B:$I,7,FALSE)<=60,"31-60 Days","61+ Days"))))
... A500: =IF(BILLING!B500="","",BILLING!B500) | B500: =IF(A500="","",IFERROR(VLOOKUP(VLOOKUP(VLOOKUP(A500,BILLING!$B:$I,7,FALSE),BOOKINGS!$A:$Q,3,FALSE),CLIENTS!$A:$H,2,FALSE),"")) | C500: =IF(A500="","",IFERROR(VLOOKUP(A500,BILLING!$B:$I,5,FALSE),0)) | E500: =IF(A500="","",C500-IFERROR(D500,0)) | G500: =IF(A500="","",IF(E500<=0,"Paid",IF(D500>0,"Partial","Unpaid"))) | H500: =IF(OR(A500="",F500=""),"",F500-VLOOKUP(A500,BILLING!$B:$I,7,FALSE)) | I500: =IF(A500="","",IF(E500<=0,"Current",IF(TODAY()-VLOOKUP(A500,BILLING!$B:$I,7,FALSE)<=30,"0-30 Days",IF(TODAY()-VLOOKUP(A500,BILLING!$B:$I,7,FALSE)<=60,"31-60 Days","61+ Days"))))

Sheet TRIP_EVALUATION
A1: Booking ID | B1: Truck Score (1-5) | C1: Driver Score (1-5) | D1: Helper Score (1-5) | E1: Delay (mins) | F1: Breakdown? | G1: Customer Rating | H1: Remarks | I1: Vehicle Class | J1: Driver Class | K1: Helper Class
I2: =IF(B2="","",IF(B2>=4,"A",IF(B2>=3,"B","C"))) | J2: =IF(C2="","",IF(C2>=4,"A",IF(C2>=3,"B","C"))) | K2: =IF(D2="","",IF(D2>=4,"A",IF(D2>=3,"B","C")))
I3: =IF(B3="","",IF(B3>=4,"A",IF(B3>=3,"B","C"))) | J3: =IF(C3="","",IF(C3>=4,"A",IF(C3>=3,"B","C"))) | K3: =IF(D3="","",IF(D3>=4,"A",IF(D3>=3,"B","C")))
I4: =IF(B4="","",IF(B4>=4,"A",IF(B4>=3,"B","C"))) | J4: =IF(C4="","",IF(C4>=4,"A",IF(C4>=3,"B","C"))) | K4: =IF(D4="","",IF(D4>=4,"A",IF(D4>=3,"B","C")))
I5: =IF(B5="","",IF(B5>=4,"A",IF(B5>=3,"B","C"))) | J5: =IF(C5="","",IF(C5>=4,"A",IF(C5>=3,"B","C"))) | K5: =IF(D5="","",IF(D5>=4,"A",IF(D5>=3,"B","C")))
I6: =IF(B6="","",IF(B6>=4,"A",IF(B6>=3,"B","C"))) | J6: =IF(C6="","",IF(C6>=4,"A",IF(C6>=3,"B","C"))) | K6: =IF(D6="","",IF(D6>=4,"A",IF(D6>=3,"B","C")))
I7: =IF(B7="","",IF(B7>=4,"A",IF(B7>=3,"B","C"))) | J7: =IF(C7="","",IF(C7>=4,"A",IF(C7>=3,"B","C"))) | K7: =IF(D7="","",IF(D7>=4,"A",IF(D7>=3,"B","C")))
I8: =IF(B8="","",IF(B8>=4,"A",IF(B8>=3,"B","C"))) | J8: =IF(C8="","",IF(C8>=4,"A",IF(C8>=3,"B","C"))) | K8: =IF(D8="","",IF(D8>=4,"A",IF(D8>=3,"B","C")))
I9: =IF(B9="","",IF(B9>=4,"A",IF(B9>=3,"B","C"))) | J9: =IF(C9="","",IF(C9>=4,"A",IF(C9>=3,"B","C"))) | K9: =IF(D9="","",IF(D9>=4,"A",IF(D9>=3,"B","C")))
I10: =IF(B10="","",IF(B10>=4,"A",IF(B10>=3,"B","C"))) | J10: =IF(C10="","",IF(C10>=4,"A",IF(C10>=3,"B","C"))) | K10: =IF(D10="","",IF(D10>=4,"A",IF(D10>=3,"B","C")))
I11: =IF(B11="","",IF(B11>=4,"A",IF(B11>=3,"B","C"))) | J11: =IF(C11="","",IF(C11>=4,"A",IF(C11>=3,"B","C"))) | K11: =IF(D11="","",IF(D11>=4,"A",IF(D11>=3,"B","C")))
I12: =IF(B12="","",IF(B12>=4,"A",IF(B12>=3,"B","C"))) | J12: =IF(C12="","",IF(C12>=4,"A",IF(C12>=3,"B","C"))) | K12: =IF(D12="","",IF(D12>=4,"A",IF(D12>=3,"B","C")))
I13: =IF(B13="","",IF(B13>=4,"A",IF(B13>=3,"B","C"))) | J13: =IF(C13="","",IF(C13>=4,"A",IF(C13>=3,"B","C"))) | K13: =IF(D13="","",IF(D13>=4,"A",IF(D13>=3,"B","C")))
... I500: =IF(B500="","",IF(B500>=4,"A",IF(B500>=3,"B","C"))) | J500: =IF(C500="","",IF(C500>=4,"A",IF(C500>=3,"B","C"))) | K500: =IF(D500="","",IF(D500>=4,"A",IF(D500>=3,"B","C")))

Sheet DASHBOARD
A1: TRUCKING OPERATIONS DASHBOARD
A2: KPI | B2: Value | C2: KPI | D2: Value
A3: Total Bookings | B3: =COUNTA(BOOKINGS!A2:A500) -> 0 | C3: Completed Trips | D3: =COUNTIF(BOOKINGS!L2:L500,"Completed") -> 0
A4: Confirmed/Assigned Trips | B4: =COUNTIF(BOOKINGS!L2:L500,"Confirmed")+COUNTIF(BOOKINGS!L2:L500,"Assigned")+COUNTIF(BOOKINGS!L2:L500,"Dispatched") -> 0 | C4: Cancelled Trips | D4: =COUNTIF(BOOKINGS!L2:L500,"Cancelled") -> 0
A5: Total Quoted Revenue | B5: =SUM(BOOKINGS!M2:M500) -> 0 | C5: Total Cost | D5: =SUM(COSTING!I2:I500) -> 0
A6: Total Profit | B6: =SUM(PROFITABILITY!D2:D500) -> 0 | C6: Avg Margin % | D6: =IFERROR(AVERAGE(PROFITABILITY!E2:E500),"")
A7: Total Invoiced | B7: =SUM(BILLING!F2:F500) -> 0 | C7: Outstanding Receivables | D7: =SUM(COLLECTIONS!E2:E500) -> 0
A8: Collected Amount | B8: =SUM(COLLECTIONS!D2:D500) -> 0 | C8: Overdue Invoices | D8: =COUNTIF(BILLING!G2:G500,"Overdue") -> 0
A9: Active Trucks | B9: =COUNTIF(SETUP_TRUCKS!F2:F484,"Active") -> 15 | C9: Active Drivers | D9: =COUNTIF(SETUP_DRIVERS!F2:F499,"Active") -> 9
A10: Avg Truck Score | B10: =IFERROR(AVERAGE(TRIP_EVALUATION!B2:B500),"") | C10: Avg Driver Score | D10: =IFERROR(AVERAGE(TRIP_EVALUATION!C2:C500),"")
A11: Loss-Making Trips | B11: =COUNTIF(PROFITABILITY!H2:H500,"LOSS") -> 0 | C11: Low-Margin Trips | D11: =COUNTIF(PROFITABILITY!H2:H500,"LOW MARGIN") -> 0
A12: Top Client by Revenue | B12: {=IFERROR(INDEX(CLIENTS!B2:B500,MATCH(LOOKUP(1.E+308,SUMIF(BOOKINGS!C2:C500,CLIENTS!A2:A500,BOOKINGS!M2:M500)),SUMIF(BOOKINGS!C2:C500,CLIENTS!A2:A500,BOOKINGS!M2:M500),0)),"See Clients")} -> ROBINSONS APPLIANCES CORP | C12: Current Month Revenue | D12: =SUMIFS(BOOKINGS!M2:M500,BOOKINGS!Q2:Q500,TEXT(TODAY(),"yyyy-mm")) -> 0
A14: CONTROL INPUTS
A15: Target Margin % | B15: =SETUP_RATES!K5 -> 0.2 | C15: Default VAT % | D15: =SETUP_RATES!K4 -> 0.12
A16: Waiting Rate/Hr | B16: =SETUP_RATES!K3 -> 500 | C16: Free Waiting Hours | D16: =SETUP_RATES!K2 -> 1
